LICENSE
README.md
setup.cfg
setup.py
FormatOC/JSON.py
FormatOC/__init__.py
format_oc.egg-info/PKG-INFO
format_oc.egg-info/SOURCES.txt
format_oc.egg-info/dependency_links.txt
format_oc.egg-info/requires.txt
format_oc.egg-info/top_level.txt
format_oc.egg-info/zip-safe